README.rst
setup.cfg
setup.py
conguide/CHANGELOG.rst
conguide/WORKFLOW.rst
conguide/__init__.py
conguide/arisia-csv.py
conguide/arisia.cfg
conguide/backup.py
conguide/bios.py
conguide/changes.py
conguide/config.py
conguide/conguide.py
conguide/count.py
conguide/dup.py
conguide/featured.py
conguide/grid.py
conguide/guidebook.py
conguide/openclose.py
conguide/outoforder.py
conguide/output.py
conguide/overnight.py
conguide/parserhelp.py
conguide/participant.py
conguide/problems.py
conguide/room.py
conguide/sasquan-xml.py
conguide/sasquan.cfg
conguide/schedule.py
conguide/session.py
conguide/times.py
conguide/tracks.py
conguide/xref.py
conguide.egg-info/PKG-INFO
conguide.egg-info/SOURCES.txt
conguide.egg-info/dependency_links.txt
conguide.egg-info/entry_points.txt
conguide.egg-info/requires.txt
conguide.egg-info/top_level.txt