Metadata-Version: 1.1
Name: conguide
Version: 0.9.7.1
Summary: Scripts to create a "Convention Guide" or "Pocket Program"
Home-page: https://github.com/pselkirk/conguide
Author: Paul Selkirk
Author-email: paul@psgd.org
License: ISC
Keywords: sf-convention publications InDesign
Platform: UNKNOWN
Classifier: Development Status :: 3 - Alpha
Classifier: Intended Audience :: End Users/Desktop
Classifier: Topic :: Other/Nonlisted Topic
Classifier: License :: OSI Approved :: ISC License (ISCL)
Classifier: Programming Language :: Python :: 2
Classifier: Programming Language :: Python :: 2.7
Classifier: Programming Language :: Python :: 3
Classifier: Programming Language :: Python :: 3.5
Classifier: Environment :: Console
Classifier: Natural Language :: English
